{
  "escalation": {
    "score": 8.5,
    "delta": "+0.3 from yesterday",
    "level": "High",
    "rationale": "US airstrikes entered their sixth consecutive night targeting Iranian infrastructure including Chabahar port and bridges in Hormozgan province, while Iran struck US Navy facilities in Bahrain and threatened full regional oil export blockade, with Houthis placed on standby to close Bab al-Mandeb."
  },
  "ticker_items": [
    "US collapses tower at Iran's Chabahar port in sixth night of strikes.",
    "Iran IRGC claims strike on US Navy facilities in Bahrain.",
    "Iran asks Houthis to prepare Bab al-Mandeb closure as oil prices surge.",
    "US Senate advances sweeping Russia sanctions bill targeting China and India.",
    "Russia drops five guided bombs on Ukraine's Sumy, hitting civilian infrastructure."
  ],
  "new_entrant": {
    "active": true,
    "text": "Houthi forces in Yemen are being activated by Iran as a potential second front, with orders to prepare drone and missile strikes to close Bab al-Mandeb strait, effectively entering the US-Iran conflict as a proxy belligerent."
  },
  "strikes_today": {
    "eastern_europe": [
      {
        "time_utc": "Unknown",
        "attacker": "Russia",
        "target_country": "Ukraine",
        "target_location": "Sumy",
        "description": "Russia dropped five guided bombs on Sumy, striking civilian infrastructure.",
        "method": "Air/Precision Strike",
        "lat": 50.91,
        "lng": 34.8,
        "source_tier": "unverified"
      }
    ],
    "middle_east": [
      {
        "time_utc": "Unknown",
        "attacker": "United States",
        "target_country": "Iran",
        "target_location": "Chabahar port, Hormozgan province",
        "description": "US airstrikes collapsed a surveillance tower at Iran's Chabahar port on the Gulf of Oman, a key trade route for Afghanistan, confirmed by US Defense Secretary Pete Hegseth.",
        "method": "Air/Precision Strike",
        "lat": 25.29,
        "lng": 60.62,
        "source_tier": "verified"
      },
      {
        "time_utc": "Unknown",
        "attacker": "United States",
        "target_country": "Iran",
        "target_location": "Hormozgan province bridges",
        "description": "US airstrikes hit and destroyed multiple bridges overnight in Iran's southern Hormozgan province, killing at least seven people according to Iranian state television.",
        "method": "Air/Precision Strike",
        "lat": 27.18,
        "lng": 56.27,
        "source_tier": "unverified"
      },
      {
        "time_utc": "Unknown",
        "attacker": "Iran (IRGC)",
        "target_country": "United States",
        "target_location": "Bahrain (US Navy facilities)",
        "description": "Iran's IRGC claimed it struck US Navy facilities in Bahrain and warned of a full regional oil and gas export blockade.",
        "method": "Missile/Surface",
        "lat": 26.21,
        "lng": 50.59,
        "source_tier": "unverified"
      }
    ]
  },
  "casualties": {
    "today": [
      {
        "incident": "US strikes on Hormozgan bridges",
        "kia": "~7",
        "wia": "Unknown",
        "civilian": true,
        "source_tier": "unverified"
      },
      {
        "incident": "US strikes on Iran - cumulative Iranian claims",
        "kia": "dozens",
        "wia": "hundreds",
        "civilian": true,
        "source_tier": "unverified"
      },
      {
        "incident": "Russian guided bomb strike on Sumy",
        "kia": "Unknown",
        "wia": "Unknown",
        "civilian": true,
        "source_tier": "unverified"
      }
    ],
    "claimed_totals": [
      {
        "claim": "Total killed in Iran (US-Israel campaign, cumulative)",
        "figure": "~3,468",
        "claimed_by": "Al Jazeera casualty tracker",
        "as_of": "2026-06-10"
      },
      {
        "claim": "Total killed in Lebanon (US-Israel campaign, cumulative)",
        "figure": "~3,696",
        "claimed_by": "Al Jazeera casualty tracker",
        "as_of": "2026-06-10"
      },
      {
        "claim": "Killed in Gulf states (US-Israel campaign, cumulative)",
        "figure": "~28",
        "claimed_by": "Al Jazeera casualty tracker",
        "as_of": "2026-06-10"
      },
      {
        "claim": "Russian troops surviving average battlefield tenure",
        "figure": "~30 minutes average survival time",
        "claimed_by": "CIA Director John Ratcliffe",
        "as_of": "2026-07-17"
      }
    ]
  },
  "quotes": {
    "russia": [],
    "ukraine": [
      {
        "text": "Ukraine will build 5 million drones in 2026; NATO must learn how.",
        "speaker": "Johnny Stringer",
        "title": "NATO Deputy Commander, Air Chief Marshal",
        "date": "2026-07-16"
      }
    ],
    "middle_east": [
      {
        "text": "We are winning big in Iran.",
        "speaker": "Donald Trump",
        "title": "US President",
        "date": "2026-07-17"
      },
      {
        "text": "Regional oil and gas exports could be blocked entirely in response to American attempts to control the Strait of Hormuz.",
        "speaker": "IRGC spokesperson",
        "title": "Islamic Revolutionary Guard Corps",
        "date": "2026-07-17"
      },
      {
        "text": "Israel is determined to keep its forces in security zones it has carved out inside Lebanon, Syria and the Gaza Strip.",
        "speaker": "Israel Katz",
        "title": "Israeli Defence Minister",
        "date": "2026-07-16"
      }
    ]
  },
  "observers": [
    {
      "country": "United States",
      "flag": "\ud83c\uddfa\ud83c\uddf8",
      "status": "Active materiel + troops",
      "description": "The US is conducting its sixth consecutive night of airstrikes against Iranian infrastructure including ports and bridges in Hormozgan province. US Defense Secretary Pete Hegseth publicly confirmed the Chabahar port strike. The Senate is also advancing sweeping Russia sanctions legislation with White House backing."
    },
    {
      "country": "Iran",
      "flag": "\ud83c\uddee\ud83c\uddf7",
      "status": "Active materiel + troops",
      "description": "Iran's IRGC claimed strikes on US Navy facilities in Bahrain and has reportedly instructed Houthi allies to prepare to close Bab al-Mandeb. Iran has resumed its Strait of Hormuz blockade, significantly reducing shipping traffic, and warned of full regional oil export closure."
    },
    {
      "country": "Israel",
      "flag": "\ud83c\uddee\ud83c\uddf1",
      "status": "Active materiel + troops",
      "description": "Israel confirmed to US Defense Secretary Hegseth that it intends to maintain troops in security zones inside Lebanon, Syria, and Gaza. Former NSA Meir Ben-Shabbat warned against retreats in Lebanon amid the broader US-Iran conflict. Over half of House Democrats revolted against a $3.3 billion aid package to Israel."
    },
    {
      "country": "Yemen (Houthis)",
      "flag": "\ud83c\uddfe\ud83c\uddea",
      "status": "Active materiel + troops",
      "description": "Iran has reportedly instructed its Houthi allies to prepare drones and missiles for potential closure of the Bab al-Mandeb strait. This would add a second major maritime chokepoint to the conflict. Houthi activation would significantly escalate the regional energy supply crisis."
    },
    {
      "country": "Russia",
      "flag": "\ud83c\uddf7\ud83c\uddfa",
      "status": "Active materiel + troops",
      "description": "Russia conducted guided bomb strikes on Sumy targeting civilian infrastructure. A bipartisan US Senate bill proposes 100% tariffs on the top buyers of Russian oil including China and India, which has White House backing. Russia is also offering India joint production of next-generation T-90MS tanks."
    },
    {
      "country": "China",
      "flag": "\ud83c\udde8\ud83c\uddf3",
      "status": "Strategic balancer",
      "description": "China faces potential US secondary sanctions as one of the largest buyers of Russian oil under the advancing Senate bill. Xi Jinping recently visited North Korea's Kim Jong Un, pledging closer diplomatic, law enforcement, and military cooperation. China-North Korea alignment is deepening amid geopolitical fragmentation."
    },
    {
      "country": "North Korea",
      "flag": "\ud83c\uddf0\ud83c\uddf5",
      "status": "Active materiel + troops",
      "description": "Kim Jong Un met with a top Chinese official following Xi's visit, with both sides pledging closer military cooperation. North Korea's activities near the DMZ are raising concerns in South Korea about potential armistice violations. Pyongyang is exploiting geopolitical fragmentation to evade nuclear sanctions."
    },
    {
      "country": "India",
      "flag": "\ud83c\uddee\ud83c\uddf3",
      "status": "Strategic balancer",
      "description": "India is named as one of the top five buyers of Russian oil potentially targeted by the US Senate sanctions bill, creating significant diplomatic pressure on New Delhi. Russia is simultaneously offering India joint T-90MS tank production. India is navigating competing pressures from Washington and Moscow."
    },
    {
      "country": "Ukraine",
      "flag": "\ud83c\uddfa\ud83c\udde6",
      "status": "Active materiel + troops",
      "description": "Zelensky's dismissal of Defense Minister Fedorov has triggered protest rallies across Ukraine and concerns about defense leadership stability. Lockheed Martin has signaled support for Ukraine producing PAC-3 interceptors domestically. Ukraine is on pace to build 5 million drones in 2026, with AI-powered systems inflicting severe Russian casualties."
    }
  ],
  "financial": {
    "usd_rub": "Unchanged",
    "brent_crude": "Rising",
    "wheat_futures": "Unchanged",
    "notes": "Oil prices rose sharply on Friday as intensifying US-Iran hostilities and Iran's threat to close both Strait of Hormuz and Bab al-Mandeb stoked supply disruption fears, with Rystad Energy revising its US-Iran scenario framework citing renewed Hormuz security deterioration."
  },
  "update_log": [
    {
      "time": "07:23",
      "text": "US airstrikes collapse surveillance tower at Iran's Chabahar port on Gulf of Oman in sixth consecutive night of attacks; confirmed by US SecDef Hegseth.",
      "source_tier": "verified"
    },
    {
      "time": "06:00",
      "text": "US strikes destroy multiple bridges in Iran's Hormozgan province overnight, killing at least seven civilians per Iranian state media.",
      "source_tier": "unverified"
    },
    {
      "time": "05:30",
      "text": "Iran's IRGC claims strike on US Navy facilities in Bahrain and threatens total blockade of regional oil and gas exports.",
      "source_tier": "unverified"
    },
    {
      "time": "04:00",
      "text": "Iran reportedly instructs Houthi forces in Yemen to prepare drone and missile capabilities to close Bab al-Mandeb strait.",
      "source_tier": "unverified"
    },
    {
      "time": "03:00",
      "text": "Russia drops five guided bombs on Sumy, Ukraine, striking civilian infrastructure.",
      "source_tier": "unverified"
    },
    {
      "time": "02:00",
      "text": "US Senate bipartisan bill proposing 100% tariffs on top Russian oil buyers including China and India advances with White House backing.",
      "source_tier": "unverified"
    },
    {
      "time": "01:00",
      "text": "North Korean leader Kim Jong Un meets top Chinese official following Xi's visit pledging closer military and diplomatic cooperation.",
      "source_tier": "verified"
    },
    {
      "time": "00:30",
      "text": "Israel's Defense Minister tells US SecDef Hegseth that Israel will maintain forces in security zones in Lebanon, Syria, and Gaza.",
      "source_tier": "unverified"
    },
    {
      "time": "00:00",
      "text": "CIA Director Ratcliffe states Russian troops survive an average of 30 minutes on the Ukrainian battlefield due to AI-powered drone attacks.",
      "source_tier": "unverified"
    }
  ],
  "last_updated": "2026-07-18T07:23:05Z"
}