{
  "escalation": {
    "score": 7,
    "delta": "No previous score available",
    "level": "Elevated",
    "rationale": "Fragile US-Iran ceasefire immediately threatened by Israeli strikes on Lebanon killing 250+, while Trump threatens NATO withdrawal."
  },
  "ticker_items": [
    "Israel kills 250+ in Lebanon strikes hours after US-Iran ceasefire",
    "Iran threatens to abort ceasefire over Israeli Lebanon attacks",
    "Trump threatens NATO exit after closed-door meeting",
    "UK-Norway forces deter Russian submarines in North Atlantic",
    "Saudi oil pipeline hit in Iranian drone attack"
  ],
  "new_entrant": {
    "active": false,
    "text": ""
  },
  "strikes_today": {
    "eastern_europe": [
      {
        "time_utc": "Unknown",
        "attacker": "Russia",
        "target_country": "Ukraine",
        "target_location": "Multiple locations",
        "description": "Russian spring offensive continues with massive drone and missile barrage on civilian areas.",
        "method": "Air/Drone",
        "lat": 50.45,
        "lng": 30.52,
        "source_tier": "verified"
      }
    ],
    "middle_east": [
      {
        "time_utc": "Unknown",
        "attacker": "Iran",
        "target_country": "Saudi Arabia",
        "target_location": "East-West Pipeline",
        "description": "Iranian drone strike hits Saudi Arabia's East-West oil pipeline pumping station.",
        "method": "Air/Drone",
        "lat": 24.71,
        "lng": 46.68,
        "source_tier": "unverified"
      },
      {
        "time_utc": "Unknown",
        "attacker": "Israel",
        "target_country": "Lebanon",
        "target_location": "Southern Lebanon",
        "description": "Israel launches largest assault on Lebanon since invasion began, targeting Hezbollah positions.",
        "method": "Air/Precision Strike",
        "lat": 33.27,
        "lng": 35.2,
        "source_tier": "unverified"
      },
      {
        "time_utc": "Unknown",
        "attacker": "Unknown",
        "target_country": "Kuwait",
        "target_location": "Kuwait",
        "description": "Drone strike on Kuwaiti territory, Kuwait blames Iran and proxies.",
        "method": "Air/Drone",
        "lat": 29.34,
        "lng": 47.66,
        "source_tier": "unverified"
      },
      {
        "time_utc": "Unknown",
        "attacker": "Israel",
        "target_country": "Lebanon",
        "target_location": "Beirut",
        "description": "Israeli forces conducted massive bombardment killing at least 250 people in heaviest attack since war began.",
        "method": "Air/Precision Strike",
        "lat": 33.89,
        "lng": 35.5,
        "source_tier": "unverified"
      },
      {
        "time_utc": "Unknown",
        "attacker": "Iran",
        "target_country": "Saudi Arabia",
        "target_location": "East-West Pipeline",
        "description": "Iranian drone struck pumping station on Saudi Arabia's East-West oil pipeline.",
        "method": "Air/Drone",
        "lat": 25.0,
        "lng": 47.0,
        "source_tier": "unverified"
      }
    ]
  },
  "casualties": {
    "today": [
      {
        "incident": "Israeli strikes Lebanon",
        "kia": "254",
        "wia": "Unknown",
        "civilian": true,
        "source_tier": "verified"
      },
      {
        "incident": "Israeli strikes on Lebanon",
        "kia": "250+",
        "wia": "Unknown",
        "civilian": true,
        "source_tier": "unverified"
      }
    ],
    "claimed_totals": [
      {
        "claim": "Iran conflict total deaths",
        "figure": "2,076 Iran, 26 Israel, 13 US, 28 Gulf states",
        "claimed_by": "Al Jazeera",
        "as_of": "2026-04-07"
      },
      {
        "claim": "US-Iran conflict total deaths",
        "figure": "~2,143",
        "claimed_by": "Al Jazeera tracker",
        "as_of": "April 10, 2026"
      }
    ]
  },
  "quotes": {
    "russia": [],
    "ukraine": [],
    "middle_east": [
      {
        "text": "Remember Greenland, that big, poorly run, piece of ice!!!",
        "speaker": "Donald Trump",
        "title": "US President",
        "date": "2026-04-09"
      },
      {
        "text": "Any ceasefire agreement to halt fighting between Tehran and Washington must explicitly include an end to Israeli military attacks in Lebanon",
        "speaker": "Iranian officials",
        "title": "Iranian Foreign Ministry",
        "date": "2026-04-08"
      },
      {
        "text": "NATO wasn't there when we needed them",
        "speaker": "Donald Trump",
        "title": "US President",
        "date": "2026-04-09"
      },
      {
        "text": "Ceasefire violations carry explicit costs and strong responses",
        "speaker": "Mohammad Bagher Ghalibaf",
        "title": "Iran Parliament Speaker",
        "date": "April 9, 2026"
      },
      {
        "text": "The military will be hanging around in Iran, won't go anywhere",
        "speaker": "Pete Hegseth",
        "title": "US Defense Secretary",
        "date": "April 9, 2026"
      }
    ]
  },
  "observers": [
    {
      "country": "Libya",
      "flag": "\ud83c\uddf1\ud83c\uddfe",
      "status": "Basing + logistics",
      "description": "Ukrainian covert forces operating in western Libya under Western-endorsed deal used Libyan territory to strike Russian tanker in Mediterranean. Two Libyan officials confirmed the arrangement allowing Ukrainian operations from their soil."
    },
    {
      "country": "Japan",
      "flag": "\ud83c\uddef\ud83c\uddf5",
      "status": "Monitoring",
      "description": "Mitsui OSK Lines monitoring US-Iran ceasefire implementation before allowing vessels through Strait of Hormuz. Major shipping company taking cautious approach to testing strategic waterway amid fragile truce."
    },
    {
      "country": "Pakistan",
      "flag": "\ud83c\uddf5\ud83c\uddf0",
      "status": "Mediator + arms supplier",
      "description": "Pakistan successfully brokered the two-week US-Iran ceasefire agreement announced April 7. Islamabad is now hosting the first direct US-Iran peace talks as Israeli attacks threaten the fragile truce."
    },
    {
      "country": "Norway",
      "flag": "\ud83c\uddf3\ud83c\uddf4",
      "status": "Active materiel + troops",
      "description": "Norwegian military forces joined UK-led operation to deter Russian submarines in North Atlantic. Reports suggest Norway is also providing specialists to Ukraine for potential maritime sabotage operations against Russian vessels."
    },
    {
      "country": "United Kingdom",
      "flag": "\ud83c\uddec\ud83c\udde7",
      "status": "Active materiel + troops",
      "description": "UK military exposed covert Russian submarine operations in British waters, forcing vessels to retreat. British and Norwegian forces conducted weeks-long deterrent operation against Russian submarines suspected of malign activity in North Atlantic."
    }
  ],
  "financial": {
    "usd_rub": "Unchanged",
    "brent_crude": "Record highs",
    "wheat_futures": "Unchanged",
    "notes": "Oil prices reaching record highs due to Iran's continued blockade of Strait of Hormuz despite ceasefire."
  },
  "update_log": [
    {
      "time": "12:41 UTC",
      "text": "Analysis shows fragile US-Iran ceasefire threatened by Israeli strikes killing 250+ in Lebanon",
      "source_tier": "unverified"
    },
    {
      "time": "12:35 UTC",
      "text": "Iran threatens to abort ceasefire if Israel continues Lebanon attacks",
      "source_tier": "unverified"
    },
    {
      "time": "12:30 UTC",
      "text": "Trump reportedly discussed leaving NATO after closed-door meeting",
      "source_tier": "unverified"
    },
    {
      "time": "12:25 UTC",
      "text": "UK and Norway completed operation deterring Russian submarines in North Atlantic",
      "source_tier": "unverified"
    },
    {
      "time": "07:13 UTC",
      "text": "Kuwait blames Iran for overnight drone strike, Iran denies responsibility",
      "source_tier": "unverified"
    },
    {
      "time": "06:45 UTC",
      "text": "Israel launches largest Lebanon assault since invasion began, 254 killed in single day",
      "source_tier": "verified"
    },
    {
      "time": "05:30 UTC",
      "text": "Trump criticizes NATO over Iran war after closed-door meeting with Secretary General Rutte",
      "source_tier": "unverified"
    },
    {
      "time": "04:15 UTC",
      "text": "Iranian drone reportedly strikes Saudi East-West oil pipeline pumping station",
      "source_tier": "unverified"
    }
  ],
  "last_updated": "2026-04-10T12:41:01Z"
}